CHANGELOG.md
README.md
config.template
mlbv/__init__.py
mlbv/mlbam/__init__.py
mlbv/mlbam/common/__init__.py
mlbv/mlbam/common/config.py
mlbv/mlbam/common/displayutil.py
mlbv/mlbam/common/gamedata.py
mlbv/mlbam/common/request.py
mlbv/mlbam/common/session.py
mlbv/mlbam/common/stream.py
mlbv/mlbam/common/util.py
mlbv/mlbam/gamedata.py.dataclass
mlbv/mlbam/mlbapidata.py
mlbv/mlbam/mlbconfig.py
mlbv/mlbam/mlbgamedata.py
mlbv/mlbam/mlbsession.py
mlbv/mlbam/mlbstream.py
mlbv/mlbam/mlbv.py
mlbv/mlbam/standings.py
mlbv/mlbam/stats.py
mlbv/mlbam/test.py
mlbv/mlbv.drawio
mlbv/test/__init__.py
mlbv/test/test_util.py
mlbv-fzf
mlbv-0.0.19.dist-info/entry_points.txt
mlbv-0.0.19.dist-info/LICENSE
mlbv-0.0.19.dist-info/WHEEL
mlbv-0.0.19.dist-info/METADATA
mlbv-0.0.19.dist-info/RECORD
