Metadata-Version: 2.1
Name: mlbv
Version: 0.0.19
Summary: Command-line interface to MLB game information, game schedule and scores
Home-page: https://github.com/kmac/mlbv
License: GPL-3.0-only
Keywords: cli,streaming,baseball,mlb,live-game
Author: kmac
Author-email: 135567+kmac@users.noreply.github.com
Requires-Python: >=3.6,<4.0
Classifier: Environment :: Console
Classifier: Intended Audience :: End Users/Desktop
Classifier: License :: OSI Approved :: GNU General Public License v3 (GPLv3)
Classifier: Programming Language :: Python :: 3
Classifier: Programming Language :: Python :: 3.10
Classifier: Programming Language :: Python :: 3.6
Classifier: Programming Language :: Python :: 3.7
Classifier: Programming Language :: Python :: 3.8
Classifier: Programming Language :: Python :: 3.9
Requires-Dist: flake8 (>=3.9.2,<4.0.0)
Requires-Dist: lxml (>=4.6.5,<5.0.0)
Requires-Dist: python-dateutil (>=2.8.1,<3.0.0)
Requires-Dist: requests (>=2.25.1,<3.0.0)
Requires-Dist: streamlink (>=2.1.1,<3.0.0)
Project-URL: Bug Reports, https://github.com/kmac/mlbv/issues
Project-URL: Repository, https://github.com/kmac/mlbv
